DSD/Lab4/Q1/FA/q1FA.v
module q1FA(x1,x2,x3,f1,f2);
    input x1,x2,x3;
    output f1,f2;
    assign f1=x1^x2^x3;
    assign a1=x1&x2;
    assign a2=x1&x3;
    assign a3=x2&x3;
    assign f2=a1|a2|a3;
endmodule

DSD/Lab4/Q1/FA/q1FA_tb.v
`timescale 1ns/1ns
`include "q1FA.v"
module q1FA_tb();
reg x1,x2,x3;
wire f1,f2;
q1FA q(x1,x2,x3,f1,f2);
initial
begin
$dumpfile("q1FA_tb.vcd");
$dumpvars(0, q1FA_tb);
	x1=1'b0; x2=1'b0; x3=1'b0; #20;
	x1=1'b0; x2=1'b0; x3=1'b1; #20;
	x1=1'b0; x2=1'b1; x3=1'b0; #20;
	x1=1'b0; x2=1'b1; x3=1'b1; #20;
	x1=1'b1; x2=1'b0; x3=1'b0; #20;
	x1=1'b1; x2=1'b0; x3=1'b1; #20;
	x1=1'b1; x2=1'b1; x3=1'b0; #20;	
	x1=1'b1; x2=1'b1; x3=1'b1; #20;
	$display ("TEST SUCESSFULL");
end
endmodule

DSD/Lab4/Q1/FA/q1FA_tb.vcd
$date
	Thu Sep 15 09:58:30 2022
$end
$version
	Icarus Verilog
$end
$timescale
	1ns
$end
$scope module q1FA_tb $end
$var wire 1 ! f2 $end
$var wire 1 " f1 $end
$var reg 1 # x1 $end
$var reg 1 $ x2 $end
$var reg 1 % x3 $end
$scope module q $end
$var wire 1 & a1 $end
$var wire 1 ' a2 $end
$var wire 1 ( a3 $end
$var wire 1 " f1 $end
$var wire 1 ! f2 $end
$var wire 1 # x1 $end
$var wire 1 $ x2 $end
$var wire 1 % x3 $end
$upscope $end
$upscope $end
$enddefinitions $end
#0
$dumpvars
0(
0'
0&
0%
0$
0#
0"
0!
$end
#20
1"
1%
#40
0%
1$
#60
1!
0"
1(
1%
#80
0!
1"
0(
0%
0$
1#
#100
1!
0"
1'
1%
#120
0'
1&
0%
1$
#140
1"
1'
1(
1%
