DSD/Lab7/q2b.v
module mux21 (w0, w1, s, f);
input w0, w1, s;
output reg f;
always @(w0 or w1 or s)
begin
	if(s==0)
		assign f=w0;
	else
		assign f=w1;
end
endmodule

module q2b(x,y,z,f);
input x,y,z;
output f;

mux21 stage1(1'b0,z,y,f0);
mux21 stage2(z,1'b1,y,f1);
mux21 stage3(f0,f1,x,f);
endmodule

DSD/Lab7/q2b_tb.v
`timescale 1ns/1ns
`include "q2b.v"

module q2b_tb();
reg x,y,z; 
wire f;

q2b m1(x,y,z,f);
initial
begin
$dumpfile("q2b_tb.vcd");
$dumpvars(0,q2b_tb);

x=0;y=0;z=0;#20;
x=0;y=0;z=1;#20;
x=0;y=1;z=0;#20;
x=0;y=1;z=1;#20;
x=1;y=0;z=0;#20;
x=1;y=0;z=1;#20;
x=1;y=1;z=0;#20;
x=1;y=1;z=1;#20;

$display("Test Complete");
end
endmodule

DSD/Lab7/q2b_tb.vcd
$date
	Thu Oct 20 08:53:50 2022
$end
$version
	Icarus Verilog
$end
$timescale
	1ns
$end
$scope module q2b_tb $end
$var wire 1 ! f $end
$var reg 1 " x $end
$var reg 1 # y $end
$var reg 1 $ z $end
$scope module m1 $end
$var wire 1 " x $end
$var wire 1 # y $end
$var wire 1 $ z $end
$var wire 1 % f1 $end
$var wire 1 & f0 $end
$var wire 1 ! f $end
$scope module stage1 $end
$var wire 1 # s $end
$var wire 1 ' w0 $end
$var wire 1 $ w1 $end
$var reg 1 & f $end
$upscope $end
$scope module stage2 $end
$var wire 1 # s $end
$var wire 1 $ w0 $end
$var wire 1 ( w1 $end
$var reg 1 % f $end
$upscope $end
$scope module stage3 $end
$var wire 1 " s $end
$var wire 1 & w0 $end
$var wire 1 % w1 $end
$var reg 1 ! f $end
$upscope $end
$upscope $end
$upscope $end
$enddefinitions $end
#0
$dumpvars
1(
0'
0&
0%
0$
0#
0"
0!
$end
#20
1%
1$
#40
1%
0$
1#
#60
1!
1&
1$
#80
0%
0!
0&
0$
0#
1"
#100
1!
1%
1$
#120
1!
1%
0$
1#
#140
1&
1$
