DSD/Lab1/Q1/Structural/q1.v
module q1(a,b,c,d,f);
	input a,b,c,d;
	output f;
	and (a1,a,b);
	and (a2,a,b);
	or (c1,a1,c);
	or (c2,a2,c);
	not (k,c1);
	and (j,k,d);
	or (i,c2,d);
	and (f,j,i);
endmodule

DSD/Lab1/Q1/Structural/q1_tb.v
`timescale 1ns/1ns
`include "q1.v"
module q1_tb();
reg a,b,c,d;
wire f;
q1 qu1(a,b,c,d,f);
initial
begin
$dumpfile("q1_tb.vcd");
$dumpvars(0, q1_tb);
	a=1'b0; b=1'b0; c=1'b0; d=1'b0; #20;
	a=1'b0; b=1'b0; c=1'b0; d=1'b1; #20;
	a=1'b0; b=1'b0; c=1'b1; d=1'b0; #20;
	a=1'b0; b=1'b0; c=1'b1; d=1'b1; #20;
	a=1'b0; b=1'b1; c=1'b0; d=1'b0; #20;
	a=1'b0; b=1'b1; c=1'b0; d=1'b1; #20;
	a=1'b0; b=1'b1; c=1'b1; d=1'b0; #20;	
	a=1'b0; b=1'b1; c=1'b1; d=1'b1; #20;
	a=1'b0; b=1'b0; c=1'b0; d=1'b0; #20;
	a=1'b1; b=1'b0; c=1'b0; d=1'b1; #20;
	a=1'b1; b=1'b0; c=1'b1; d=1'b0; #20;
	a=1'b1; b=1'b0; c=1'b1; d=1'b1; #20;
	a=1'b1; b=1'b1; c=1'b0; d=1'b0; #20;
	a=1'b1; b=1'b1; c=1'b0; d=1'b1; #20;
	a=1'b1; b=1'b1; c=1'b1; d=1'b0; #20;
	a=1'b1; b=1'b1; c=1'b1; d=1'b1; #20;
	$display ("TEST SUCESSFULL");
end
endmodule

DSD/Lab1/Q1/Structural/q1_tb.vcd
$date
	Thu Aug 25 10:48:16 2022
$end
$version
	Icarus Verilog
$end
$timescale
	1ns
$end
$scope module q1_tb $end
$var wire 1 ! f $end
$var reg 1 " a $end
$var reg 1 # b $end
$var reg 1 $ c $end
$var reg 1 % d $end
$scope module qu1 $end
$var wire 1 " a $end
$var wire 1 & a1 $end
$var wire 1 ' a2 $end
$var wire 1 # b $end
$var wire 1 $ c $end
$var wire 1 ( c1 $end
$var wire 1 ) c2 $end
$var wire 1 % d $end
$var wire 1 ! f $end
$var wire 1 * i $end
$var wire 1 + j $end
$var wire 1 , k $end
$upscope $end
$upscope $end
$enddefinitions $end
#0
$dumpvars
1,
0+
0*
0)
0(
0'
0&
0%
0$
0#
0"
0!
$end
#20
1!
1+
1*
1%
#40
0!
0,
0+
1(
1)
0%
1$
#60
1%
#80
1,
0*
0(
0)
0%
0$
1#
#100
1!
1+
1*
1%
#120
0!
0,
0+
1(
1)
0%
1$
#140
1%
#160
1,
0*
0(
0)
0%
0$
0#
#180
1!
1+
1*
1%
1"
#200
0!
0,
0+
1(
1)
0%
1$
#220
1%
#240
1&
1'
0%
0$
1#
#260
1%
#280
0%
1$
#300
1%
