DSD/Lab4/Q1/DA/q1DA.v
module q1DA(x,y,c,s,cout);
    input x,y,c;
    output s,cout;
    assign f1=x^y;
    assign f2=x&y;
    assign s=f1^c;
    assign f4=f1&c;
    assign cout=f4|f2;
endmodule

DSD/Lab4/Q1/DA/q1DA_tb.v
`timescale 1ns/1ns
`include "q1DA.v"
module q1DA_tb();
reg x,y,c;
wire s,cout;
q1DA q(x,y,c,s,cout);
initial
begin
$dumpfile("q1DA_tb.vcd");
$dumpvars(0, q1DA_tb);
	x=1'b0; y=1'b0; c=1'b0; #20;
	x=1'b0; y=1'b0; c=1'b1; #20;
	x=1'b0; y=1'b1; c=1'b0; #20;
	x=1'b0; y=1'b1; c=1'b1; #20;
	x=1'b1; y=1'b0; c=1'b0; #20;
	x=1'b1; y=1'b0; c=1'b1; #20;
	x=1'b1; y=1'b1; c=1'b0; #20;	
	x=1'b1; y=1'b1; c=1'b1; #20;
	$display ("TEST SUCESSFULL");
end
endmodule

DSD/Lab4/Q1/DA/q1DA_tb.vcd
$date
	Thu Sep 15 10:19:59 2022
$end
$version
	Icarus Verilog
$end
$timescale
	1ns
$end
$scope module q1DA_tb $end
$var wire 1 ! s $end
$var wire 1 " cout $end
$var reg 1 # c $end
$var reg 1 $ x $end
$var reg 1 % y $end
$scope module q $end
$var wire 1 # c $end
$var wire 1 " cout $end
$var wire 1 & f1 $end
$var wire 1 ' f2 $end
$var wire 1 ( f4 $end
$var wire 1 ! s $end
$var wire 1 $ x $end
$var wire 1 % y $end
$upscope $end
$upscope $end
$enddefinitions $end
#0
$dumpvars
0(
0'
0&
0%
0$
0#
0"
0!
$end
#20
1!
1#
#40
1&
0#
1%
#60
1"
0!
1(
1#
#80
0"
1!
0(
0#
0%
1$
#100
1"
0!
1(
1#
#120
0(
0&
1'
0#
1%
#140
1!
1#
