DSD/Lab6/q1.v
module q1(w,s,f);
    input [3:0] w;
    input [1:0] s;
    output f;
    wire [1:0] ft;  
    MUX2to1 stage0(w[1:0],s[0],ft[0]);
    MUX2to1 stage1(w[3:2],s[0],ft[1]);
    MUX2to1 stage2(ft,s[1],f);

endmodule

module MUX2to1(w,s,f);
    input [1:0] w;
    input s;
    output f;
    reg f;

    always @(w or s)
    begin 
        f = w[1];
        if(s == 0)
            f = w[0];
    end
endmodule

DSD/Lab6/q1_tb.v
`timescale 1ns/1ns
`include "q1.v"

module q1_tb();     
reg [3:0] w;
reg [1:0] s;
wire f;

q1 qu(w,s,f);
initial 
begin 
    $dumpfile("q1_tb.vcd");
    $dumpvars(0,q1_tb);

    w = 4'b0001;
    s = 2'b00; #20;
    s = 2'b01; #20;
    s = 2'b10; #20;
    s = 2'b01; #20;

    w = 4'b1010;
    s = 2'b00; #20;
    s = 2'b01; #20;
    s = 2'b10; #20;
    s = 2'b01; #20;

    $display("Test Complete");

end
endmodule

DSD/Lab6/q1_tb.vcd
$date
	Thu Oct  6 10:27:55 2022
$end
$version
	Icarus Verilog
$end
$timescale
	1ns
$end
$scope module q1_tb $end
$var wire 1 ! f $end
$var reg 2 " s [1:0] $end
$var reg 4 # w [3:0] $end
$scope module qu $end
$var wire 2 $ s [1:0] $end
$var wire 4 % w [3:0] $end
$var wire 2 & ft [1:0] $end
$var wire 1 ! f $end
$scope module stage0 $end
$var wire 1 ' s $end
$var wire 2 ( w [1:0] $end
$var reg 1 ) f $end
$upscope $end
$scope module stage1 $end
$var wire 1 * s $end
$var wire 2 + w [1:0] $end
$var reg 1 , f $end
$upscope $end
$scope module stage2 $end
$var wire 1 - s $end
$var wire 2 . w [1:0] $end
$var reg 1 ! f $end
$upscope $end
$upscope $end
$upscope $end
$enddefinitions $end
#0
$dumpvars
b1 .
0-
0,
b0 +
0*
1)
b1 (
0'
b1 &
b1 %
b0 $
b1 #
b0 "
1!
$end
#20
0!
b0 &
b0 .
0)
1'
1*
b1 "
b1 $
#40
b1 &
b1 .
1)
0'
0*
1-
b10 "
b10 $
#60
b0 &
b0 .
0)
0!
1'
1*
0-
b1 "
b1 $
#80
0)
b0 &
b0 .
0,
0'
0*
b10 (
b10 +
b0 "
b0 $
b1010 #
b1010 %
#100
1!
1)
b11 &
b11 .
1,
1'
1*
b1 "
b1 $
#120
0!
0)
b0 &
b0 .
0,
0'
0*
1-
b10 "
b10 $
#140
1!
1)
b11 &
b11 .
1,
1'
1*
0-
b1 "
b1 $
