lab9/q1.v
module q1(W, En,f);
input [3:0] W;
input En;
output f;
wire [15:0] Y;
dec4to16 decoder(W,Y,En);
assign f= Y[1] | Y[3] | Y[6] | Y[7] | Y[9] | Y[14] | Y[15];
endmodule

module dec4to16(w,y,En);
input [3:0] w;
input En;
output [15:0] y;

wire t1,t2;
assign t1 = ~w[3] & En;
assign t2 = w[3] & En;

threeTo8Decoder stage0(w[2:0],t1,y[7:0]);
threeTo8Decoder stage1(w[2:0],t2,y[15:8]);

endmodule

module threeTo8Decoder(w,En,y);
    input [2:0] w;
    input En;
    output reg [7:0] y;

    integer k;

    always @(w or En)
        for(k = 0; k <= 7; k=k+1)
        if ((w == k) && (En == 1))
            y[k] = 1;
        else 
            y[k] = 0;

endmodule

lab9/q1_tb.v
`timescale 1ns/1ns
`include "q1.v"
module q1_tb();
reg [3:0] W;
reg En;
wire f;
q1 s1(W,En,f);
initial
begin
	$dumpfile("q1_tb.vcd");
	$dumpvars(0, q1_tb);
W = 0; En=1;
#20;
W = 1; En=1;
#20;
W = 2; En=1;
#20;
W = 3; En=1;
#20;
W = 4; En=1;
#20;
W = 5; En=1;
#20;
W = 6; En=1;
#20;
W = 7; En=1;
#20;
W = 8; En=1;
#20;
W = 9; En=1;
#20;
W = 10; En=1;
#20;
W =11; En=1;
#20;
W = 12; En=1;
#20;
W = 13; En=1;
#20;
W = 14; En=1;
#20;
W = 15; En=1;
#20;
	$display("Test complete");
end
endmodule

DSD/lab9/q1_tb.vcd
$date
	Thu Oct 27 09:18:26 2022
$end
$version
	Icarus Verilog
$end
$timescale
	1ns
$end
$scope module q1_tb $end
$var wire 1 ! f $end
$var reg 1 " En $end
$var reg 4 # W [3:0] $end
$scope module s1 $end
$var wire 1 " En $end
$var wire 4 $ W [3:0] $end
$var wire 1 ! f $end
$var wire 16 % Y [15:0] $end
$scope module decoder $end
$var wire 1 " En $end
$var wire 1 & t1 $end
$var wire 1 ' t2 $end
$var wire 4 ( w [3:0] $end
$var wire 16 ) y [15:0] $end
$scope module stage0 $end
$var wire 1 & En $end
$var wire 3 * w [2:0] $end
$var reg 8 + y [7:0] $end
$var integer 32 , k [31:0] $end
$upscope $end
$scope module stage1 $end
$var wire 1 ' En $end
$var wire 3 - w [2:0] $end
$var reg 8 . y [7:0] $end
$var integer 32 / k [31:0] $end
$upscope $end
$upscope $end
$upscope $end
$upscope $end
$enddefinitions $end
#0
$dumpvars
b1000 /
b0 .
b0 -
b1000 ,
b1 +
b0 *
b1 )
b0 (
0'
1&
b1 %
b0 $
b0 #
1"
0!
$end
#20
1!
b10 %
b10 )
b10 +
b1000 ,
b1000 /
b1 *
b1 -
b1 #
b1 $
b1 (
#40
0!
b100 %
b100 )
b100 +
b1000 ,
b1000 /
b10 *
b10 -
b10 #
b10 $
b10 (
#60
1!
b1000 %
b1000 )
b1000 +
b1000 ,
b1000 /
b11 *
b11 -
b11 #
b11 $
b11 (
#80
0!
b10000 %
b10000 )
b10000 +
b1000 ,
b1000 /
b100 *
b100 -
b100 #
b100 $
b100 (
#100
b100000 %
b100000 )
b100000 +
b1000 ,
b1000 /
b101 *
b101 -
b101 #
b101 $
b101 (
#120
1!
b1000000 %
b1000000 )
b1000000 +
b1000 ,
b1000 /
b110 *
b110 -
b110 #
b110 $
b110 (
#140
b10000000 %
b10000000 )
b10000000 +
b1000 ,
b1000 /
b111 *
b111 -
b111 #
b111 $
b111 (
#160
0!
0&
b1 .
1'
b100000000 %
b100000000 )
b0 +
b1000 ,
b1000 /
b0 *
b0 -
b1000 #
b1000 $
b1000 (
#180
1!
b1000 ,
b1000000000 %
b1000000000 )
b10 .
b1000 /
b1 *
b1 -
b1001 #
b1001 $
b1001 (
#200
0!
b1000 ,
b10000000000 %
b10000000000 )
b100 .
b1000 /
b10 *
b10 -
b1010 #
b1010 $
b1010 (
#220
b1000 ,
b100000000000 %
b100000000000 )
b1000 .
b1000 /
b11 *
b11 -
b1011 #
b1011 $
b1011 (
#240
b1000 ,
b1000000000000 %
b1000000000000 )
b10000 .
b1000 /
b100 *
b100 -
b1100 #
b1100 $
b1100 (
#260
b1000 ,
b10000000000000 %
b10000000000000 )
b100000 .
b1000 /
b101 *
b101 -
b1101 #
b1101 $
b1101 (
#280
1!
b1000 ,
b100000000000000 %
b100000000000000 )
b1000000 .
b1000 /
b110 *
b110 -
b1110 #
b1110 $
b1110 (
#300
b1000 ,
b1000000000000000 %
b1000000000000000 )
b10000000 .
b1000 /
b111 *
b111 -
b1111 #
b1111 $
b1111 (
