DSD/Lab1/Q2/Behave/qtwo.v
module qtwo (a,b,c,d,f,g);
	input a,b,c,d;
	output f,g;
	assign f=((~(a&b))^d^c);
	assign g=~(b|c|d);
endmodule

DSD/Lab1/Q2/Behave/qtwo_tb.v
`timescale 1ns/1ns
`include "qtwo.v"
module qtwo_tb();
reg a,b,c,d;
wire f,g;
qtwo qu2(a,b,c,d,f,g);
initial
begin
$dumpfile("qtwo_tb.vcd");
$dumpvars(0, qtwo_tb);
	a=1'b0; b=1'b0; c=1'b0; d=1'b0; #20;
	a=1'b0; b=1'b0; c=1'b0; d=1'b1; #20;
	a=1'b0; b=1'b0; c=1'b1; d=1'b0; #20;
	a=1'b0; b=1'b0; c=1'b1; d=1'b1; #20;
	a=1'b0; b=1'b1; c=1'b0; d=1'b0; #20;
	a=1'b0; b=1'b1; c=1'b0; d=1'b1; #20;
	a=1'b0; b=1'b1; c=1'b1; d=1'b0; #20;	
	a=1'b0; b=1'b1; c=1'b1; d=1'b1; #20;
	a=1'b0; b=1'b0; c=1'b0; d=1'b0; #20;
	a=1'b1; b=1'b0; c=1'b0; d=1'b1; #20;
	a=1'b1; b=1'b0; c=1'b1; d=1'b0; #20;
	a=1'b1; b=1'b0; c=1'b1; d=1'b1; #20;
	a=1'b1; b=1'b1; c=1'b0; d=1'b0; #20;
	a=1'b1; b=1'b1; c=1'b0; d=1'b1; #20;
	a=1'b1; b=1'b1; c=1'b1; d=1'b0; #20;
	a=1'b1; b=1'b1; c=1'b1; d=1'b1; #20;
	$display ("TEST SUCESSFULL");
end
endmodule

DSD/Lab1/Q2/Behave/qtwo_tb.vcd
$date
	Thu Aug 25 11:26:13 2022
$end
$version
	Icarus Verilog
$end
$timescale
	1ns
$end
$scope module qtwo_tb $end
$var wire 1 ! g $end
$var wire 1 " f $end
$var reg 1 # a $end
$var reg 1 $ b $end
$var reg 1 % c $end
$var reg 1 & d $end
$scope module qu2 $end
$var wire 1 # a $end
$var wire 1 $ b $end
$var wire 1 % c $end
$var wire 1 & d $end
$var wire 1 " f $end
$var wire 1 ! g $end
$upscope $end
$upscope $end
$enddefinitions $end
#0
$dumpvars
0&
0%
0$
0#
1"
1!
$end
#20
0"
0!
1&
#40
0"
0&
1%
#60
1"
1&
#80
1"
0&
0%
1$
#100
0"
1&
#120
0"
0&
1%
#140
1"
1&
#160
1!
1"
0&
0%
0$
#180
0"
0!
1&
1#
#200
0"
0&
1%
#220
1"
1&
#240
0"
0&
0%
1$
#260
1"
1&
#280
1"
0&
1%
#300
0"
1&
